{
  "task_id": "legal_reasoning_causality",
  "name": "legal_reasoning_causality",
  "family": "LegalBench",
  "description": "Classify whether a district court opinion excerpt relies on statistical evidence in its reasoning for finding causality.",
  "dataset_url": "https://hazyresearch.stanford.edu/legalbench/",
  "num_samples": 59,
  "tags": [
    "labor law",
    "rhetorical understanding"
  ],
  "document_type": "judicial text",
  "min_input_length": 141,
  "max_input_length": 1018,
  "metrics": [
    {
      "name": "accuracy",
      "direction": "maximize"
    },
    {
      "name": "balanced_accuracy",
      "direction": "maximize"
    },
    {
      "name": "f1_macro",
      "direction": "maximize"
    },
    {
      "name": "f1_micro",
      "direction": "maximize"
    },
    {
      "name": "valid_predictions_ratio",
      "direction": "maximize"
    }
  ],
  "contributed_by_name": "Neel Guha",
  "contributed_by_email": "nguha@cs.stanford.edu",
  "paper_url": "https://arxiv.org/abs/2308.11462",
  "paper_title": "LegalBench: A Collaboratively Built Benchmark for Measuring Legal Reasoning in Large Language Models",
  "paper_authors": [
    "Neel Guha",
    "Julian Nyarko",
    "Daniel E. Ho",
    "Christopher R\u00e9",
    "Adam Chilton",
    "Aditya Narayana",
    "Alex Chohlas-Wood",
    "Austin Peters",
    "Brandon Waldon",
    "Daniel N. Rockmore",
    "Diego Zambrano",
    "Dmitry Talisman",
    "Enam Hoque",
    "Faiz Surani",
    "Frank Fagan",
    "Galit Sarfaty",
    "Gregory M. Dickinson",
    "Haggai Porat",
    "Jason Hegland",
    "Jessica Wu",
    "Joe Nudell",
    "Joel Niklaus",
    "John Nay",
    "Jonathan H. Choi",
    "Kevin Tobia",
    "Margaret Hagan",
    "Megan Ma",
    "Michael Livermore",
    "Nikon Rasumov-Rahe",
    "Nils Holzenberger",
    "Noam Kolt",
    "Peter Henderson",
    "Sean Rehaag",
    "Sharad Goel",
    "Shang Gao",
    "Spencer Williams",
    "Sunny Gandhi",
    "Tom Zur",
    "Varun Iyer",
    "Zehua Li"
  ],
  "source": "Haggai Porat, Tom Zur",
  "license": "[CC BY 4.0](https://creativecommons.org/licenses/by/4.0/)",
  "legal_reasoning_type": "Rhetorical-analysis",
  "task_type": "Binary classification"
}